pyktug/__init__.py
pyktug/data.py
pyktug/data_info.py
pyktug/dict_to_json.py
pyktug/gait_analysis.py
pyktug/gait_speed.py
pyktug/html_generator.py
pyktug/joint_angles.py
pyktug/phases_tug.py
pyktug/plotting.py
pyktug/smart_chair.py
pyktug/tools.py
pyktug/utils.py
pyktug_guilleeh90-0.0.2.1.dist-info/LICENSE
pyktug_guilleeh90-0.0.2.1.dist-info/METADATA
pyktug_guilleeh90-0.0.2.1.dist-info/WHEEL
pyktug_guilleeh90-0.0.2.1.dist-info/top_level.txt
pyktug_guilleeh90-0.0.2.1.dist-info/RECORD
