Metadata-Version: 2.1
Name: pyktug-guilleeh90
Version: 0.0.2.1
Summary: Data analysis in TUG test for Kinect v2
Home-page: https://github.com/guilleeh90
Author: Guillermo Díaz
Author-email: guillermodiazsm@gmail.com
License: MIT
Platform: UNKNOWN
Classifier: Programming Language :: Python :: 3
Classifier: License :: OSI Approved :: MIT License
Classifier: Operating System :: OS Independent
Requires-Python: >=3.6
